conpass/__init__.py
conpass/console.py
conpass/core.py
conpass/gpo.py
conpass/ldapconnection.py
conpass/ntlminfo.py
conpass/password.py
conpass/pso.py
conpass/session.py
conpass/user.py
conpass/utils.py
conpass-0.1.2.dist-info/LICENSE
conpass-0.1.2.dist-info/METADATA
conpass-0.1.2.dist-info/WHEEL
conpass-0.1.2.dist-info/entry_points.txt
conpass-0.1.2.dist-info/top_level.txt
conpass-0.1.2.dist-info/zip-safe
conpass-0.1.2.dist-info/RECORD
