Metadata-Version: 2.1
Name: conpass
Version: 0.1.2
Summary: Continuous password spraying tool
Home-page: https://github.com/Hackndo/conpass/
Author: Pixis
Author-email: hackndo@gmail.com
License: MIT
Classifier: Programming Language :: Python :: 3.6
Classifier: Programming Language :: Python :: 3.7
Classifier: Programming Language :: Python :: 3.8
Classifier: Programming Language :: Python :: 3.9
Classifier: Programming Language :: Python :: 3.10
Classifier: Programming Language :: Python :: 3.11
Classifier: Programming Language :: Python :: 3.12
Classifier: License :: OSI Approved :: MIT License
Classifier: Operating System :: OS Independent
Requires-Python: >=3.6
License-File: LICENSE
Requires-Dist: python-ldap
Requires-Dist: impacket
Requires-Dist: rich
